california_house_price_predictor_7606/__init__.py
california_house_price_predictor_7606/ingest_data.py
california_house_price_predictor_7606/score.py
california_house_price_predictor_7606/train.py
california_house_price_predictor_7606-1.0.0.dist-info/LICENSE
california_house_price_predictor_7606-1.0.0.dist-info/METADATA
california_house_price_predictor_7606-1.0.0.dist-info/WHEEL
california_house_price_predictor_7606-1.0.0.dist-info/top_level.txt
california_house_price_predictor_7606-1.0.0.dist-info/RECORD
