Metadata-Version: 2.1
Name: california-house-price-predictor-7606
Version: 1.0.0
Summary: california's housing price prediction ML model
Author-email: "devaraj.saravana" <devaraj.saravana@tigeranalytics.com>
License: Copyright (c) 2018 The Python Packaging Authority        
Project-URL: Homepage, https://github.com/devaraj-saravana/pypi
Project-URL: Bug Tracker, https://github.com/devaraj-saravana/pypi/issues
Classifier: Programming Language :: Python :: 3
Classifier: License :: OSI Approved :: MIT License
Classifier: Operating System :: OS Independent
Requires-Python: >=3.7
License-File: LICENSE
